ArchPy/__init__.py
ArchPy/_version.py
ArchPy/ap_mf.py
ArchPy/automatic_pile.py
ArchPy/base.py
ArchPy/data_transfo.py
ArchPy/ineq.py
ArchPy/infer.py
ArchPy/inputs.py
ArchPy/parallel.py
ArchPy/tpgs.py
ArchPy/uppy.py
ArchPy/x_valid.py
geoarchpy-1.2.11.dist-info/licenses/LICENSE
geoarchpy-1.2.11.dist-info/METADATA
geoarchpy-1.2.11.dist-info/WHEEL
geoarchpy-1.2.11.dist-info/top_level.txt
geoarchpy-1.2.11.dist-info/RECORD
