Metadata-Version: 2.4
Name: Geoarchpy
Version: 1.2.11
Summary: Simpler geological and property models
Home-page: https://github.com/randlab/ArchPy
Author: Ludovic Schorpp
Author-email: ludovic.schorpp@unine.ch
License:                     GNU GENERAL PUBLIC LICENSE
License-File: LICENSE
Requires-Dist: matplotlib
Requires-Dist: numpy<2,>=1
Requires-Dist: scipy
Requires-Dist: scikit-learn
Requires-Dist: scikit-image
Requires-Dist: geone
Requires-Dist: pandas
Requires-Dist: shapely
Provides-Extra: all
Requires-Dist: pyvista; extra == "all"
Requires-Dist: trame; extra == "all"
Requires-Dist: trame-vuetify; extra == "all"
Requires-Dist: trame-vtk; extra == "all"
Requires-Dist: notebook; extra == "all"
Requires-Dist: ipywidgets; extra == "all"
Requires-Dist: ipympl; extra == "all"
Requires-Dist: pyyaml; extra == "all"
Requires-Dist: rasterio; extra == "all"
Requires-Dist: geopandas; extra == "all"
Requires-Dist: flopy; extra == "all"
Requires-Dist: numba; extra == "all"
Requires-Dist: pyshp; extra == "all"
Requires-Dist: seaborn; extra == "all"
Dynamic: author
Dynamic: author-email
Dynamic: description
Dynamic: description-content-type
Dynamic: home-page
Dynamic: license
Dynamic: license-file
Dynamic: provides-extra
Dynamic: requires-dist
Dynamic: summary
